ecs_shell.py
ecs_shell-1.0.0.dist-info/licenses/LICENSE
ecs_shell-1.0.0.dist-info/METADATA
ecs_shell-1.0.0.dist-info/WHEEL
ecs_shell-1.0.0.dist-info/entry_points.txt
ecs_shell-1.0.0.dist-info/top_level.txt
ecs_shell-1.0.0.dist-info/RECORD
