Metadata-Version: 2.4
Name: ecs-shell
Version: 1.0.0
Summary: Interactive shell for AWS ECS tasks with service and task selection.
Home-page: https://github.com/yourusername/ecs-shell
Author: Francisco
License: MIT
Keywords: aws,ecs,shell,docker,container,devops
Classifier: Development Status :: 4 - Beta
Classifier: Environment :: Console
Classifier: Intended Audience :: Developers
Classifier: License :: OSI Approved :: MIT License
Classifier: Topic :: Utilities
Classifier: Topic :: System :: Systems Administration
Classifier: Programming Language :: Python :: 3
Classifier: Programming Language :: Python :: 3.10
Classifier: Programming Language :: Python :: 3.11
Classifier: Programming Language :: Python :: 3.12
Classifier: Programming Language :: Python :: 3.13
Requires-Python: >=3.10
License-File: LICENSE
Requires-Dist: boto3>=1.40.76
Requires-Dist: inquirer>=3.4.1
Requires-Dist: rich>=14.2.0
Dynamic: author
Dynamic: classifier
Dynamic: description
Dynamic: description-content-type
Dynamic: home-page
Dynamic: keywords
Dynamic: license
Dynamic: license-file
Dynamic: requires-dist
Dynamic: requires-python
Dynamic: summary
